{
  "debug_info": {
    "full_text": "F8 Tributo '19\nDrivetrain MR / Aspiration TC\nEngine Model F154CG-F8\n\nBase Performance\n\nPerformance Points PP 697.60\nMax. Power 526 BHP\nMax. Torque 60.8 kgim\nDisplacement 3,902 cc\nWeight 1,405 kg\nFront-Rear Weight Balance 44 : 56\n\nAcceleration Performance\n\n0-0.25 miles 10.75 sec.\n0-0.62 miles 19.82 sec.\n62-93 mph 2.12 sec.\nStability\nLow Speed -0.13 (Neutral)\nHigh Speed -1.00 (Under)\nRotational G\n40 mph 1.32 6G\n75 mph 1.40G\n150 mph 1.63 G\n\nFerrari {9\n\n@\u00ae Measure\n\nMeasurement\nHistory\n\nLi @q@p Ri\n\n697.60\n526\n60.8\n3,902\n1,405\n44 : 56\n\n10.75\n19.82\n2.72\n\n-0.13\n-1.00\n\n1.32\n1.40\n1.63\n\nSettings Sheet 1\n\nEdit Settings Sheet\n\nTyres Aerodynamics\nFront \u2014] Racing: Hard v \u2014 \u2014\nDownforce Ly. 300 500\nRear \u2014 Racing: Hard v ECU\nSuspension ECU Fully Customisable *\nSuspension Fully Customisable v Output Adjustment % 77\nFront oe Performance Adjustment\nBody Height Adjustment mm 90 95 Ballast kg 75\nAnti-Roll Bar a 6 10 Ballast Positioning -46\neee 4 27 28 Power Restrictor % 91\nDamping Ratio (Expansion) % 36 37 - Transmission\nNatural Frequency Hz 3.50 3.50 Transmission Fully Customisable: Racing VY\nNegative Camber Angle 2 2.3 2.9 Meee (Automatically |), 340\n\nToe Angle .\n\nDifferential\n\nInitial Torque Lv.\nAcceleration Sensitivity Lv.\nBraking Sensitivity Lv.\n\nTorque-Vectoring Centre\nDifferential\n\nFront/Rear Torque Distribution\n\nvi a\nDifferential Gear\n\n#4.0.01\n\nManual Adjustment Ooo\n\n~ Nitrous/Overtake\n\nFully Customisable v tion\n\nNitrous/Overtake None v\nFront Rear\n0 14 Output Adjustment % (@)\n17\n0 12\nNone\n0: 100\n\n(\u00a9 2025 Sony interactive Entertainment Inc. Developed by Polyphony Digital inc.\n",
    "vehicle_name": "F8 Tributo '19",
    "vehicle_weight": "1,405",
    "front_weight_distribution": "44",
    "front_ride_height": "90",
    "rear_ride_height": "95",
    "front_downforce": "300",
    "rear_downforce": "50C",
    "low_speed_stability": "-0.13",
    "high_speed_stability": "-1.00",
    "rotational_g_40mph": "1.32",
    "rotational_g_75mph": "1.40",
    "rotational_g_150mph": "1.63",
    "performance_points": "697.60",
    "front_tires": ") Racing: Hard",
    "rear_tires": ") Racing: Hard"
  },
  "results": {
    "vehicle_weight": 1405,
    "front_weight_distribution": 44,
    "front_downforce": 300,
    "rear_downforce": 50,
    "low_speed_stability": -0.13,
    "high_speed_stability": -1.0,
    "rotational_g_40mph": 1.32,
    "rotational_g_75mph": 1.4,
    "rotational_g_150mph": 1.63,
    "performance_points": 697.6,
    "front_tires": "RH",
    "rear_tires": "RH"
  }
}