{
  "debug_info": {
    "full_text": "RGT 4.2 '16\nDrivetrain RR / Aspiration TC\nEngine Model RUF386-RGT\n\nBase Performance\n\nPerformance Points pP611.78\nMax. Power 536 BHP\nMax. Torque 53.9 kgfm\nDisplacement 4,187 cc\nWeight 1,455 kg\nFront-Rear Weight Balance 40 : 60\n\nAcceleration Performance\n\n0-0.25 miles 12.06 sec.\n0-0.62 miles 21.38 sec.\n62-93 mph 2.99 sec.\nStability\nLow Speed -0.26 (Neutral)\nHigh Speed -1.00 (Under)\nRotational G\n40 mph 1.09 G\n75 mph 1.1464\n150 mph Wash (@\n\n@\u00ae Megsure\n\nMeasurement\nHistory\n\neee ee \u00a9\n\nL1\n\n<4> i\n\n599.99\n498\n50.1\n4,187\n1,464\n41:59\n\n12.33\n21.90\n3.23\n\n-0.25\n-1.00\n\n1.09\n1.14\n1.30\n\nSettings Sheet 1\n\nTyres\n\nFront \u2014] Gy) Sports: Hard M\nRear \u2014 Gy) Sports: Hard v\nSuspension\nSuspension Fully Customisable Vv\nFront Rear\nBody Height Adjustment mm 57 57\nAnti-Roll Bar Lv. 4 4\nDamping Ratio (Expansion) % 45 45\nNatural Frequency Hz 2.35 2.55\nNegative Camber Angle s 3.0 3.0\nToe Angle \u00e9 \u00a72 0.00 #4.0.20\nDifferential Gear\nDifferential Fully Customisable Vv\nFront Rear\nInitial Torque Lv. 0 10\nAcceleration Sensitivity Lv. (0) 13\nBraking Sensitivity Lv. (@) L\nDee Centre None\nFront/Rear Torque Distribution 0: 100\n\nEdit Settings Sheet\n\nAerodynamics\n\nFront Rear\nDownforce Ly. 200 450\nee ee EEG\nECU Fully Customisable v\nOutput Adjustment % 93\nPerformance Adjustment - ee\nBallast kg 64\nBallast Positioning -49\nPower Restrictor % 40)\n\nTransmission\n\nTransmission = =\n\nFully Customisable: Manual \u00a5\n\nTop Speed (Automatically km/h 300\n\nAdjusted)\n\nManual Adjustment eee\n\nNitrous/Overtake\n\nOutput Adjustment\n\n\u2014 Nitrous/Overtake -\n\nNone v\n\n% 0\n\nth\n\nth\n\n>\n\n(\u00a9 2025 Sony Interactive Entertainment Inc. Developed by Polyphony Digital inc.\n",
    "vehicle_name": "RGT 4.2 '16",
    "vehicle_weight": "1,464",
    "front_weight_distribution": "41",
    "front_ride_height": "of",
    "rear_ride_height": "57",
    "front_downforce": "200 |",
    "rear_downforce": "450",
    "low_speed_stability": "-0.25",
    "high_speed_stability": "-1.00",
    "rotational_g_40mph": "1.09",
    "rotational_g_75mph": "1.14",
    "rotational_g_150mph": "1.30",
    "performance_points": "599.99",
    "front_tires": "Sports: Hard",
    "rear_tires": "Sports: Hard"
  },
  "results": {
    "vehicle_weight": 1464,
    "front_weight_distribution": 41,
    "front_ride_height": 0,
    "rear_ride_height": 57,
    "front_downforce": 200,
    "rear_downforce": 450,
    "low_speed_stability": -0.25,
    "high_speed_stability": -1.0,
    "rotational_g_40mph": 1.09,
    "rotational_g_75mph": 1.14,
    "rotational_g_150mph": 1.3,
    "performance_points": 599.99,
    "front_tires": "SH",
    "rear_tires": "SH"
  }
}